README
setup.py
libel/__init__.py
libel/cipher.py
libel/prereq.py
libel/selectionlist.py
libel/selectors.py
libel/sentientobject.py
libel.egg-info/PKG-INFO
libel.egg-info/SOURCES.txt
libel.egg-info/dependency_links.txt
libel.egg-info/top_level.txt