Metadata-Version: 1.0
Name: libel
Version: 0.1.5
Summary: Scandalous utility functions and classes for Python.
Home-page: UNKNOWN
Author: Derek McTavish Mounce
Author-email: d.mounce@silkseed.com
License: MIT
Platform: UNKNOWN
